plantgateway-0.6.2.data/scripts/plantgateway
plantgw/__init__.py
plantgw/plantgw.py
plantgateway-0.6.2.dist-info/LICENSE
plantgateway-0.6.2.dist-info/METADATA
plantgateway-0.6.2.dist-info/WHEEL
plantgateway-0.6.2.dist-info/top_level.txt
plantgateway-0.6.2.dist-info/RECORD
