Metadata-Version: 2.1
Name: plantgateway
Version: 0.6.2
Summary: Bluetooth to mqtt gateway for Xiaomi Mi plant sensors
Home-page: https://www.python.org/sigs/distutils-sig/
Author: Christian Kühnel
Author-email: christian.kuehnel@gmail.com
License: UNKNOWN
Platform: UNKNOWN
Requires-Dist: bluepy (==1.3.0)
Requires-Dist: paho-mqtt
Requires-Dist: pyyaml (>=5.1)
Requires-Dist: miflora (==0.5)
Requires-Dist: typing (<4,>=3)
